flaggart/__init__.py
flaggart/analysis.py
flaggart/filehandling.py
flaggart/wiki_flags.py
flaggart-0.4.1.dist-info/LICENSE
flaggart-0.4.1.dist-info/WHEEL
flaggart-0.4.1.dist-info/METADATA
flaggart-0.4.1.dist-info/RECORD
